CHANGES.rst
MANIFEST.in
README.rst
buildout.cfg
minitage-buildout.cfg
minitage-test.cfg
minitage.cfg
setup.cfg
setup.py
test.cfg
examples/ajax-test.py
examples/anothergoogle.py
examples/google.py
examples/native_events.py
examples/proxy.py
examples/webkit_methods.py
examples/wordreference.py
src/spynner/__init__.py
src/spynner/browser.py
src/spynner/testing.py
src/spynner.egg-info/PKG-INFO
src/spynner.egg-info/SOURCES.txt
src/spynner.egg-info/dependency_links.txt
src/spynner.egg-info/requires.txt
src/spynner.egg-info/top_level.txt
src/spynner/javascript/__init__.py
src/spynner/javascript/jquery-1.5.2.js
src/spynner/javascript/jquery.min.js
src/spynner/javascript/jquery.simulate.js
src/spynner/javascript/test.html
src/spynner/tests/__init__.py
src/spynner/tests/base.py
src/spynner/tests/html_controls.html
src/spynner/tests/spynner.rst
src/spynner/tests/t.html
src/spynner/tests/test_doctests.py
test/test_browser.py
test/webserver.py
test/fixtures/protected.html
test/fixtures/test.css
test/fixtures/test1.html
test/fixtures/test2.html
test/fixtures/test3.html