Metadata-Version: 1.1
Name: spynner
Version: 2.14
Summary: Programmatic web browsing module with AJAX support for Python
Home-page: https://github.com/makinacorpus/spynner
Author: Arnau Sanchez, Mathieu Le Marec-Pasquet
Author-email: tokland@gmail.com, kiorky@cryptelium.net
License: GPL v3.0
Platform: UNKNOWN
Classifier: Development Status :: 3 - Alpha
Classifier: Intended Audience :: Developers
Classifier: License :: OSI Approved :: GNU General Public License (GPL)
Classifier: Natural Language :: English
Classifier: Operating System :: POSIX
Classifier: Operating System :: Microsoft :: Windows
Classifier: Programming Language :: Python
Classifier: Topic :: Internet :: WWW/HTTP
